robbo/__init__.py
robbo/__version__.py
robbo/board.py
robbo/defs.py
robbo/game.py
robbo/images.py
robbo/levels.py
robbo/sounds.py
robbo/status.py
robbo/levels/ala.dat
robbo/levels/forever.dat
robbo/levels/original.dat
robbo/levels/test.dat
robbo/skins/default/digits.png
robbo/skins/default/icons.png
robbo/skins/oily/digits.png
robbo/skins/oily/icons.png
robbo/skins/tronic/ciphers32.bmp
robbo/skins/tronic/digits.png
robbo/skins/tronic/icons.png
robbo/sounds/blaster.wav
robbo/sounds/bomb.wav
robbo/sounds/bullet.wav
robbo/sounds/die.wav
robbo/sounds/door.wav
robbo/sounds/finish.wav
robbo/sounds/key.wav
robbo/sounds/lastscrew.wav
robbo/sounds/life.wav
robbo/sounds/push.wav
robbo/sounds/screw.wav
robbo/sounds/shoot.wav
robbo/sounds/spawn.wav
robbo/sounds/teleport.wav
robbo/sounds/wallshoot.wav
robbo/sprites/__init__.py
robbo/sprites/guns.py
robbo/sprites/items.py
robbo/sprites/mobs.py
robbo/sprites/robbo.py
robbo/sprites/static.py
robbo/sprites/teleport.py
PyRobbo-0.5.0.dist-info/LICENSE
PyRobbo-0.5.0.dist-info/METADATA
PyRobbo-0.5.0.dist-info/WHEEL
PyRobbo-0.5.0.dist-info/entry_points.txt
PyRobbo-0.5.0.dist-info/top_level.txt
PyRobbo-0.5.0.dist-info/RECORD
